eod/__init__.py
eod/eod.py
eod/alternative_data/__init__.py
eod/alternative_data/alternative_financial_data.py
eod/alternative_data/economic_events_data_api/__init__.py
eod/alternative_data/economic_events_data_api/economic_events_data.py
eod/alternative_data/financial_news_api/__init__.py
eod/alternative_data/financial_news_api/financial_news.py
eod/alternative_data/macroeconomic_api/__init__.py
eod/alternative_data/macroeconomic_api/macroeconomic_data_indicators.py
eod/alternative_data/sentiment_financial_api/__init__.py
eod/alternative_data/sentiment_financial_api/sentiment.py
eod/exchanges/__init__.py
eod/exchanges/exchanges_stocks_financials.py
eod/exchanges/bulk_eod_splits_divs_api/__init__.py
eod/exchanges/bulk_eod_splits_divs_api/bulk_eod_splits_divs.py
eod/exchanges/financial_news_api/__init__.py
eod/exchanges/financial_news_api/financial_news.py
eod/exchanges/list_tickers_api/__init__.py
eod/exchanges/list_tickers_api/exchanges_and_tickers.py
eod/exchanges/search_instrument_api/__init__.py
eod/exchanges/search_instrument_api/search_instrument.py
eod/exchanges/stock_market_screener_api/__init__.py
eod/exchanges/stock_market_screener_api/stock_market_screener.py
eod/exchanges/trading_hours_market_holidays_api/__init__.py
eod/exchanges/trading_hours_market_holidays_api/trading_hours_market_holidays.py
eod/fundamental_economic_data/__init__.py
eod/fundamental_economic_data/fundamental_economic.py
eod/fundamental_economic_data/calendar_earnings_trends_ipos_splits_api/__init__.py
eod/fundamental_economic_data/calendar_earnings_trends_ipos_splits_api/calendar_earnings_trends_ipos_splits.py
eod/fundamental_economic_data/fundamental_api/__init__.py
eod/fundamental_economic_data/fundamental_api/fundamental_data.py
eod/fundamental_economic_data/historical_market_capitalization_api/__init__.py
eod/fundamental_economic_data/historical_market_capitalization_api/market_capitalization.py
eod/fundamental_economic_data/insider_transactions_api/__init__.py
eod-0.2.1.dist-info/LICENSE
eod-0.2.1.dist-info/METADATA
eod-0.2.1.dist-info/WHEEL
eod-0.2.1.dist-info/top_level.txt
eod-0.2.1.dist-info/RECORD
