Metadata-Version: 2.1
Name: eod
Version: 0.2.1
Summary: SDK for EOD Historical data APIs
Home-page: https://github.com/LautaroParada/eod-data
Author: Lautaro Parada Opazo
Author-email: lautaro.parada.opazo@gmail.com
License: Apache License 2.0
Platform: UNKNOWN
License-File: LICENSE
